Metadata-Version: 2.1
Name: odoo13-addon-product-expiry-configurable
Version: 13.0.1.0.1.dev7
Summary: This model allows setting expiry times on category and to use the 'end_of_life' date for the computation of lot dates
Home-page: https://github.com/OCA/product-attribute
Author: Odoo Community Association (OCA)
Author-email: support@odoo-community.org
License: AGPL-3
Platform: UNKNOWN
Classifier: Programming Language :: Python
Classifier: Framework :: Odoo
Classifier: Framework :: Odoo :: 13.0
Classifier: License :: OSI Approved :: GNU Affero General Public License v3
Requires-Python: >=3.5
Requires-Dist: odoo <13.1dev,>=13.0a
